[{"operationId":"wGOoybChVESqr05XrKOiXQ","operationType":"commit","parameters":{"Objects":["[Builder.TestHelper]"]},"constants":{},"allowedUserRoleSets":[["Administrator"],["User"],["Anonymous"],["DataEmployee"]]},{"operationId":"hPKyKx00n0OoZF3bJER5Ag","operationType":"rollback","parameters":{"Objects":["AnyObjectList"]},"constants":{},"allowedUserRoleSets":[["Administrator"],["User"],["Anonymous"],["DataEmployee"]]},{"operationId":"RajDqKz+bkyVig+qQBw0Jw","operationType":"rollback","parameters":{"Objects":["AnyObjectList"]},"constants":{},"allowedUserRoleSets":[["Administrator"],["User"],["Anonymous"],["DataEmployee"]]},{"operationId":"XlAobg1us068WispOiZJzQ","operationType":"delete","parameters":{"Objects":["[OQL.ExamplePerson]"]},"constants":{},"allowedUserRoleSets":[]},{"operationId":"IcB7zygfJEW35W+QoeLkjA","operationType":"callMicroflow","parameters":{"Course":["Builder.Course"],"School":["Builder.School"]},"constants":{"MicroflowName":"Builder.ACT_Course_Delete"},"allowedUserRoleSets":[["Administrator"],["DataEmployee"]]},{"operationId":"YtVqoo2p/E+8imQZ8wqPtQ","operationType":"commit","parameters":{"Objects":["[Builder.TestHelper]"]},"constants":{},"allowedUserRoleSets":[["Administrator"],["User"],["Anonymous"],["DataEmployee"]]},{"operationId":"pnhP0t0k+UeykcTyPUW4NA","operationType":"commit","parameters":{"Objects":["[Builder.TestHelper]"]},"constants":{},"allowedUserRoleSets":[["Administrator"],["User"],["Anonymous"],["DataEmployee"]]},{"operationId":"fk5tfMexGUKqjOJHZ2rbEQ","operationType":"commit","parameters":{"Objects":["[Builder.ConnectedSelector]"]},"constants":{},"allowedUserRoleSets":[["Administrator"],["User"],["Anonymous"],["DataEmployee"]]},{"operationId":"j7lDekkjjUSrknfxR1Bt+A","operationType":"callMicroflow","parameters":{"SolverTest":["Solver.SolverTest"],"SolverQuestion":["Solver.SolverQuestion"]},"constants":{"MicroflowName":"Solver.ACT_ReviewQuestion_FromSolvedTests"},"allowedUserRoleSets":[["Administrator"],["User"]]},{"operationId":"P88QcTIl4ky+yhbYr1kbUw","operationType":"callMicroflow","parameters":{"ConnectedSelector":["Builder.ConnectedSelector"]},"constants":{"MicroflowName":"Builder.DS_SelectableLectures"},"allowedUserRoleSets":[["Administrator"],["User"],["Anonymous"],["DataEmployee"]]},{"operationId":"4Yxh47GpGEqfQh/X3qr9GA","operationType":"commit","parameters":{"Objects":["[Builder.TestHelper]"]},"constants":{},"allowedUserRoleSets":[["Administrator"],["User"],["Anonymous"],["DataEmployee"]]},{"operationId":"/iIECGJapECPTpaOhmoXuA","operationType":"callMicroflow","parameters":{"ConnectedSelector":["Builder.ConnectedSelector"]},"constants":{"MicroflowName":"Builder.DS_SelectableCourses"},"allowedUserRoleSets":[["Administrator"],["User"],["Anonymous"],["DataEmployee"]]},{"operationId":"yQeRX6jpt0Owh5eJ2WUstg","operationType":"callMicroflow","parameters":{},"constants":{"MicroflowName":"Anonymous.ACT_Test_UserLocation"},"allowedUserRoleSets":[["Anonymous"]]},{"operationId":"Q8htiOlwLkKRNtf/HS9HiQ","operationType":"rollback","parameters":{"Objects":["AnyObjectList"]},"constants":{},"allowedUserRoleSets":[["Administrator"],["User"],["Anonymous"],["DataEmployee"]]},{"operationId":"fXnF3dS6+0m3mxzq9NHd3g","operationType":"callMicroflow","parameters":{"Account":["Administration.Account"]},"constants":{"MicroflowName":"Administration.ShowMyPasswordForm"},"allowedUserRoleSets":[["Administrator"],["User"],["DataEmployee"]]},{"operationId":"FCPkgQeMZEa8vnQuEQdXkw","operationType":"rollback","parameters":{"Objects":["AnyObjectList"]},"constants":{},"allowedUserRoleSets":[["Administrator"],["User"],["Anonymous"],["DataEmployee"]]},{"operationId":"bGWQIqMJrEWMID87KrY8Pw","operationType":"commit","parameters":{"Objects":["AnyObjectList"]},"constants":{},"allowedUserRoleSets":[["Administrator"],["User"],["Anonymous"],["DataEmployee"]]},{"operationId":"lbzOqSYnOE6U5Gx/UaeJRw","operationType":"create","parameters":{},"constants":{"ObjectType":"Builder.Course"},"allowedUserRoleSets":[["Administrator"],["DataEmployee"]]},{"operationId":"GnyN1Y4d0kSGPnHCKmabAw","operationType":"callMicroflow","parameters":{"TestBuilderHelper":["Builder.TestHelper"]},"constants":{"MicroflowName":"Builder.ACT_SaveTest"},"allowedUserRoleSets":[["Administrator"],["DataEmployee"]]},{"operationId":"TLKeKe6aSkSxJ5ztr43izQ","operationType":"callMicroflow","parameters":{},"constants":{"MicroflowName":"Builder.DS_ConnectedSelector"},"allowedUserRoleSets":[["Administrator"],["User"],["Anonymous"],["DataEmployee"]]},{"operationId":"LffFuQH3jUSrbShneER2VA","operationType":"commit","parameters":{"Objects":["AnyObjectList"]},"constants":{},"allowedUserRoleSets":[["Administrator"],["User"],["Anonymous"],["DataEmployee"]]},{"operationId":"uEz9aJag5UWNTkjQMBQ78A","operationType":"callMicroflow","parameters":{"ConnectedSelector":["Builder.ConnectedSelector"],"TestHelper":["Builder.TestHelper"]},"constants":{"MicroflowName":"Solver.ACT_GenerateSolverTest"},"allowedUserRoleSets":[["User"]]},{"operationId":"4Q2LlfWtFkuQbYub/55Kzg","operationType":"rollback","parameters":{"Objects":["AnyObjectList"]},"constants":{},"allowedUserRoleSets":[["Administrator"],["User"],["Anonymous"],["DataEmployee"]]},{"operationId":"ULyzORfA+EKpQbi03SlgOA","operationType":"commit","parameters":{"Objects":["AnyObjectList"]},"constants":{},"allowedUserRoleSets":[["Administrator"],["User"],["Anonymous"],["DataEmployee"]]},{"operationId":"/ljmHgMzsUqTQ4dPIi81ng","operationType":"rollback","parameters":{"Objects":["AnyObjectList"]},"constants":{},"allowedUserRoleSets":[["Administrator"],["User"],["Anonymous"],["DataEmployee"]]},{"operationId":"HzBKKLUvwkWYlUzNsUa3LQ","operationType":"rollback","parameters":{"Objects":["AnyObjectList"]},"constants":{},"allowedUserRoleSets":[["Administrator"],["User"],["Anonymous"],["DataEmployee"]]},{"operationId":"q5MThbxnrEmlfkJkvyGiqQ","operationType":"rollback","parameters":{"Objects":["AnyObjectList"]},"constants":{},"allowedUserRoleSets":[["Administrator"],["User"],["Anonymous"],["DataEmployee"]]},{"operationId":"wpj+FCmhGk6LBeFu+4pQLQ","operationType":"rollback","parameters":{"Objects":["AnyObjectList"]},"constants":{},"allowedUserRoleSets":[["Administrator"],["User"],["Anonymous"],["DataEmployee"]]},{"operationId":"06pfMk2gbUm7gE0Rmfkl2g","operationType":"callMicroflow","parameters":{"Lecture":["Builder.Lecture"],"Course":["Builder.Course"]},"constants":{"MicroflowName":"Builder.ACT_Lecture_ShowEdit"},"allowedUserRoleSets":[["Administrator"],["DataEmployee"]]},{"operationId":"Gzp1Yv6lUUC6qKDbyTOlbA","operationType":"commit","parameters":{"Objects":["[Anonymous.Anonymous]"]},"constants":{},"allowedUserRoleSets":[["Administrator"],["User"],["Anonymous"],["DataEmployee"]]},{"operationId":"dMrXfdvWOkeZB6OZL4WZwQ","operationType":"callMicroflow","parameters":{},"constants":{"MicroflowName":"OQL.IVK_PerformTests"},"allowedUserRoleSets":[]},{"operationId":"O9XqKKXvQUu4kHJCjXtIUg","operationType":"create","parameters":{},"constants":{"ObjectType":"Builder.Test"},"allowedUserRoleSets":[["Administrator"],["User"],["Anonymous"],["DataEmployee"]]},{"operationId":"6mj0rqtmr02kFm2QWxTePQ","operationType":"callMicroflow","parameters":{"Question":["Builder.Question"],"Test":["Builder.Test"]},"constants":{"MicroflowName":"Builder.ACT_DeleteQuestion"},"allowedUserRoleSets":[["Administrator"],["DataEmployee"]]},{"operationId":"492jQEfEi0uJ5ea6J18M1A","operationType":"commit","parameters":{"Objects":["[Builder.TestHelper]"]},"constants":{},"allowedUserRoleSets":[["Administrator"],["User"],["Anonymous"],["DataEmployee"]]},{"operationId":"seOHjmyIeEyiu9WuAVRynw","operationType":"commit","parameters":{"Objects":["[Builder.TestHelper]"]},"constants":{},"allowedUserRoleSets":[["Administrator"],["User"],["Anonymous"],["DataEmployee"]]},{"operationId":"fuAayR/XQ1m/yiBe+2dqNA","operationType":"callMicroflow","parameters":{"Anonymous":["Anonymous.Anonymous"]},"constants":{"MicroflowName":"Anonymous.SUB_CreateAccount"},"allowedUserRoleSets":[["Administrator"],["User"],["Anonymous"],["DataEmployee"]]},{"operationId":"ZTtD3Jm7ZUiPPp9KbGl6qQ","operationType":"callMicroflow","parameters":{"Course":["Builder.Course"],"School":["Builder.School"]},"constants":{"MicroflowName":"Builder.ACT_Course_ShowEdit"},"allowedUserRoleSets":[["Administrator"],["DataEmployee"]]},{"operationId":"SQKKsAgFBkyq1xtHgR2seg","operationType":"rollback","parameters":{"Objects":["AnyObjectList"]},"constants":{},"allowedUserRoleSets":[["Administrator"],["User"],["Anonymous"],["DataEmployee"]]},{"operationId":"0SUS0emzRUKhYMGfecwPww","operationType":"callMicroflow","parameters":{"Lecture":["Builder.Lecture"],"Course":["Builder.Course"]},"constants":{"MicroflowName":"Builder.ACT_Lecture_Delete"},"allowedUserRoleSets":[["Administrator"],["DataEmployee"]]},{"operationId":"oPxDmPZIUUiVfxNy+T1TxQ","operationType":"rollback","parameters":{"Objects":["AnyObjectList"]},"constants":{},"allowedUserRoleSets":[["Administrator"],["User"],["Anonymous"],["DataEmployee"]]},{"operationId":"zTlMCCCZgE2yAK/qjRlQyg","operationType":"create","parameters":{},"constants":{"ObjectType":"Builder.Question"},"allowedUserRoleSets":[["Administrator"],["User"],["Anonymous"],["DataEmployee"]]},{"operationId":"QVOOZC9R7E2+4m8jo9ZZRA","operationType":"callMicroflow","parameters":{},"constants":{"MicroflowName":"Administration.NewAccount"},"allowedUserRoleSets":[["Administrator"]]},{"operationId":"oGdr+1IEeEOKWjYwcEj45Q","operationType":"commit","parameters":{"Objects":["[Builder.TestHelper]"]},"constants":{},"allowedUserRoleSets":[["Administrator"],["User"],["Anonymous"],["DataEmployee"]]},{"operationId":"+jT96HuPHkKIzCnR++FK0w","operationType":"callMicroflow","parameters":{"Test":["Builder.Test"],"Question":["Builder.Question"]},"constants":{"MicroflowName":"Builder.ACT_UpdateQuestion"},"allowedUserRoleSets":[["Administrator"],["DataEmployee"]]},{"operationId":"LC+M2V+DRkS1SyEW/jh5Bw","operationType":"callMicroflow","parameters":{"ConnectedSelector":["Builder.ConnectedSelector"]},"constants":{"MicroflowName":"Builder.DS_SelectableCourses"},"allowedUserRoleSets":[["Administrator"],["User"],["Anonymous"],["DataEmployee"]]},{"operationId":"Z1Z4HRuw4k2bnsJjHRdYtA","operationType":"delete","parameters":{"Objects":["[Administration.Account]"]},"constants":{},"allowedUserRoleSets":[["Administrator"]]},{"operationId":"ubtqiEYGVEW9iJQwtF47gQ","operationType":"commit","parameters":{"Objects":["AnyObjectList"]},"constants":{},"allowedUserRoleSets":[["Administrator"],["User"],["Anonymous"],["DataEmployee"]]},{"operationId":"fv8F2K6tNEiwQMTOSEl15g","operationType":"commit","parameters":{"Objects":["AnyObjectList"]},"constants":{},"allowedUserRoleSets":[["Administrator"],["User"],["Anonymous"],["DataEmployee"]]},{"operationId":"Xx7eLzKqMkOJopAlUwUZhw","operationType":"callMicroflow","parameters":{"TestHelper":["Builder.TestHelper"]},"constants":{"MicroflowName":"Solver.DS_ActiveSolverQuestion"},"allowedUserRoleSets":[["Administrator"],["User"],["Anonymous"],["DataEmployee"]]},{"operationId":"I2N+nXdxOku3Iy6t5KqnCQ","operationType":"rollback","parameters":{"Objects":["AnyObjectList"]},"constants":{},"allowedUserRoleSets":[["Administrator"],["User"],["Anonymous"],["DataEmployee"]]},{"operationId":"DQ7fAOkElkWZlzMkPSgChQ","operationType":"callMicroflow","parameters":{},"constants":{"MicroflowName":"Administration.NewWebServiceAccount"},"allowedUserRoleSets":[["Administrator"]]},{"operationId":"jUgQYQ7oqE+iMlal2N3MPw","operationType":"rollback","parameters":{"Objects":["AnyObjectList"]},"constants":{},"allowedUserRoleSets":[["Administrator"],["User"],["Anonymous"],["DataEmployee"]]},{"operationId":"xRqTRlZegkagitsat4uoqA","operationType":"callMicroflow","parameters":{"Test":["Builder.Test"]},"constants":{"MicroflowName":"Builder.ACT_UpdateTest"},"allowedUserRoleSets":[["Administrator"],["DataEmployee"]]},{"operationId":"2TbRwQxpiEipOlzYzIciVg","operationType":"commit","parameters":{"Objects":["[Builder.TestHelper]"]},"constants":{},"allowedUserRoleSets":[["Administrator"],["User"],["Anonymous"],["DataEmployee"]]},{"operationId":"poTiBIHUAkeM6i7LlfMOvg","operationType":"callMicroflow","parameters":{"SolverTest":["Solver.SolverTest"]},"constants":{"MicroflowName":"Solver.ACT_ReviewTest_FromSolvedTests"},"allowedUserRoleSets":[["Administrator"],["User"]]},{"operationId":"Q+ZrPAJ8xUSfc7ylPl/eYw","operationType":"commit","parameters":{"Objects":["[Builder.ConnectedSelector]"]},"constants":{},"allowedUserRoleSets":[["Administrator"],["User"],["Anonymous"],["DataEmployee"]]},{"operationId":"fIpmg8xKKUGeGk0co1QRnw","operationType":"callMicroflow","parameters":{},"constants":{"MicroflowName":"OQL.DS_GetQuery"},"allowedUserRoleSets":[["Administrator"],["User"],["Anonymous"],["DataEmployee"]]},{"operationId":"9+v87V/UcEOJgDBfJ+UhAg","operationType":"callMicroflow","parameters":{"Account":["Administration.Account"]},"constants":{"MicroflowName":"Administration.ShowPasswordForm"},"allowedUserRoleSets":[["Administrator"]]},{"operationId":"1MDwh9L4J0+zxkIAF6S5gg","operationType":"callMicroflow","parameters":{},"constants":{"MicroflowName":"DataStore.ACT_Lecture_FromOQL_V1"},"allowedUserRoleSets":[["Administrator"],["User"]]},{"operationId":"hanF5px2/UeFlocQzq5cdg","operationType":"callMicroflow","parameters":{},"constants":{"MicroflowName":"OQL.IVK_CreateContent"},"allowedUserRoleSets":[]},{"operationId":"XxUC4L1ZT0O9LG6vcIkPoA","operationType":"callMicroflow","parameters":{"TestHelper":["Builder.TestHelper"]},"constants":{"MicroflowName":"Builder.DS_ActiveQuestion"},"allowedUserRoleSets":[["Administrator"],["User"],["Anonymous"],["DataEmployee"]]},{"operationId":"MtTmXWwk+U+HpzYKTkgqmQ","operationType":"delete","parameters":{"Objects":["[System.Session]"]},"constants":{},"allowedUserRoleSets":[["Administrator"],["User"],["Anonymous"],["DataEmployee"]]},{"operationId":"sZGEXQ6T8UaKb3bUjDQecw","operationType":"commit","parameters":{"Objects":["AnyObjectList"]},"constants":{},"allowedUserRoleSets":[["Administrator"],["User"],["Anonymous"],["DataEmployee"]]},{"operationId":"4yeOaT/jqU2K5hyxR2Dztg","operationType":"rollback","parameters":{"Objects":["AnyObjectList"]},"constants":{},"allowedUserRoleSets":[["Administrator"],["User"],["Anonymous"],["DataEmployee"]]},{"operationId":"pFknso4b2EGQOHe3UKP0lA","operationType":"rollback","parameters":{"Objects":["AnyObjectList"]},"constants":{},"allowedUserRoleSets":[["Administrator"],["User"],["Anonymous"],["DataEmployee"]]},{"operationId":"bUhiFge670+uJcPiuZqJ1g","operationType":"callMicroflow","parameters":{"AccountPasswordData":["Administration.AccountPasswordData"]},"constants":{"MicroflowName":"Administration.ChangePassword"},"allowedUserRoleSets":[["Administrator"]]},{"operationId":"gYYY0HE5bE242Soo4fhM9A","operationType":"rollback","parameters":{"Objects":["AnyObjectList"]},"constants":{},"allowedUserRoleSets":[["Administrator"],["User"],["Anonymous"],["DataEmployee"]]},{"operationId":"k5HdbavR60Cd4W1C1rRDwQ","operationType":"rollback","parameters":{"Objects":["AnyObjectList"]},"constants":{},"allowedUserRoleSets":[["Administrator"],["User"],["Anonymous"],["DataEmployee"]]},{"operationId":"eQUsX/3wIUOhwLcup4WOCw","operationType":"callMicroflow","parameters":{},"constants":{"MicroflowName":"Solver.ACT_GenerateSolvedTests"},"allowedUserRoleSets":[["User"]]},{"operationId":"E1c/wjpOqUarxAYjM8Eq4g","operationType":"rollback","parameters":{"Objects":["AnyObjectList"]},"constants":{},"allowedUserRoleSets":[["Administrator"],["User"],["Anonymous"],["DataEmployee"]]},{"operationId":"wxFn88VgK0SLUGby9+kYjw","operationType":"callMicroflow","parameters":{"ConnectedSelector":["Builder.ConnectedSelector"]},"constants":{"MicroflowName":"Builder.DS_SelectableLectures"},"allowedUserRoleSets":[["Administrator"],["User"],["Anonymous"],["DataEmployee"]]},{"operationId":"dK96cox2V0alKXzIb4h7Yw","operationType":"callMicroflow","parameters":{},"constants":{"MicroflowName":"OQL.DS_ExampleOQL_Statement"},"allowedUserRoleSets":[["Administrator"],["User"],["Anonymous"],["DataEmployee"]]},{"operationId":"7p2Cucl8vEuhvBJVQf4WxA","operationType":"rollback","parameters":{"Objects":["AnyObjectList"]},"constants":{},"allowedUserRoleSets":[["Administrator"],["User"],["Anonymous"],["DataEmployee"]]},{"operationId":"vCWgoVaGjkCwxBRmT8vDAg","operationType":"create","parameters":{},"constants":{"ObjectType":"Builder.School"},"allowedUserRoleSets":[["Administrator"],["DataEmployee"]]},{"operationId":"oIWv98PycE6rkJqfcvB1GQ","operationType":"rollback","parameters":{"Objects":["AnyObjectList"]},"constants":{},"allowedUserRoleSets":[["Administrator"],["User"],["Anonymous"],["DataEmployee"]]},{"operationId":"NarVUjONbECOnS1ulw14ig","operationType":"callMicroflow","parameters":{},"constants":{"MicroflowName":"Administration.RetrieveTimeZones"},"allowedUserRoleSets":[["Administrator"],["User"],["Anonymous"],["DataEmployee"]]},{"operationId":"4My1aYw4o0aLDfILm6iYPQ","operationType":"callMicroflow","parameters":{"Test":["Builder.Test"]},"constants":{"MicroflowName":"Builder.ACT_DeleteTest"},"allowedUserRoleSets":[["Administrator"],["DataEmployee"]]},{"operationId":"1y/1FVx10UOXtbTTRkeQfA","operationType":"rollback","parameters":{"Objects":["AnyObjectList"]},"constants":{},"allowedUserRoleSets":[["Administrator"],["User"],["Anonymous"],["DataEmployee"]]},{"operationId":"fqdHDDGgbkOtgcHiwkSixQ","operationType":"rollback","parameters":{"Objects":["AnyObjectList"]},"constants":{},"allowedUserRoleSets":[["Administrator"],["User"],["Anonymous"],["DataEmployee"]]},{"operationId":"AMtMqA6yLUaTQM8DgB6A5A","operationType":"create","parameters":{},"constants":{"ObjectType":"Builder.Lecture"},"allowedUserRoleSets":[["Administrator"],["DataEmployee"]]},{"operationId":"bwsGX+87ekW99JCS/Idilw","operationType":"callMicroflow","parameters":{},"constants":{"MicroflowName":"DataStore.ACT_Lecture_FromOQL_V2"},"allowedUserRoleSets":[["Administrator"],["User"]]},{"operationId":"ugnicol+HEG7CsOZk45RWQ","operationType":"callMicroflow","parameters":{},"constants":{"MicroflowName":"Extensions.SUB_Account_ByCurrentUser"},"allowedUserRoleSets":[["Administrator"],["User"],["Anonymous"],["DataEmployee"]]},{"operationId":"ENiBGI8TGk+dKLCfP1xvWw","operationType":"rollback","parameters":{"Objects":["AnyObjectList"]},"constants":{},"allowedUserRoleSets":[["Administrator"],["User"],["Anonymous"],["DataEmployee"]]},{"operationId":"6Cpzhyae2UuWFQY5iGWDIA","operationType":"callMicroflow","parameters":{"AccountPasswordData":["Administration.AccountPasswordData"]},"constants":{"MicroflowName":"Administration.SaveNewAccount"},"allowedUserRoleSets":[["Administrator"]]},{"operationId":"504i0B8Ld0WC1GTSfYDfZw","operationType":"create","parameters":{},"constants":{"ObjectType":"OQL.ExamplePerson"},"allowedUserRoleSets":[]},{"operationId":"bR1Rhip0mESx+uYJ7Rc0Bg","operationType":"delete","parameters":{"Objects":["[Builder.School]"]},"constants":{},"allowedUserRoleSets":[["Administrator"],["User"],["DataEmployee"]]},{"operationId":"F7Ax/Ri06E+JNKgXIy91PQ","operationType":"callMicroflow","parameters":{},"constants":{"MicroflowName":"Administration.RetrieveTimeZones"},"allowedUserRoleSets":[["Administrator"],["User"],["Anonymous"],["DataEmployee"]]},{"operationId":"94CvZ7sq+k+WylXIkYjBfQ","operationType":"commit","parameters":{"Objects":["[Builder.TestHelper]"]},"constants":{},"allowedUserRoleSets":[["Administrator"],["User"],["Anonymous"],["DataEmployee"]]},{"operationId":"ainnLzFJQk2xYscT9unetg","operationType":"commit","parameters":{"Objects":["[Anonymous.Anonymous]"]},"constants":{},"allowedUserRoleSets":[["Administrator"],["User"],["Anonymous"],["DataEmployee"]]},{"operationId":"wxHRlXmQdEGsFbF9OnMUyQ","operationType":"callMicroflow","parameters":{},"constants":{"MicroflowName":"Builder.DS_ConnectedSelector"},"allowedUserRoleSets":[["Administrator"],["User"],["Anonymous"],["DataEmployee"]]},{"operationId":"NjoBLH1uzku6a3EJLauUwA","operationType":"callMicroflow","parameters":{"Query":["OQL.Query"]},"constants":{"MicroflowName":"OQL.ACT_ExecuteOQL"},"allowedUserRoleSets":[]},{"operationId":"RDEDGZ6ezEO3n5ThsUR81A","operationType":"rollback","parameters":{"Objects":["AnyObjectList"]},"constants":{},"allowedUserRoleSets":[["Administrator"],["User"],["Anonymous"],["DataEmployee"]]},{"operationId":"Wur/zK8aMk6sxCF5e8pbvg","operationType":"rollback","parameters":{"Objects":["AnyObjectList"]},"constants":{},"allowedUserRoleSets":[["Administrator"],["User"],["Anonymous"],["DataEmployee"]]},{"operationId":"zPtx8lgLWUS2h9rUuzmz2w","operationType":"callMicroflow","parameters":{},"constants":{"MicroflowName":"OQL.DS_ExampleOQL_DataSet"},"allowedUserRoleSets":[["Administrator"],["User"],["Anonymous"],["DataEmployee"]]},{"operationId":"hYxgWQ5SBEG/1Yt7+Z5UZg","operationType":"callMicroflow","parameters":{},"constants":{"MicroflowName":"DataStore.ACT_BuilderTest_GetByUser"},"allowedUserRoleSets":[["Administrator"],["User"]]},{"operationId":"G8Wp1ZKcwkihQFYTnVF05g","operationType":"rollback","parameters":{"Objects":["AnyObjectList"]},"constants":{},"allowedUserRoleSets":[["Administrator"],["User"],["Anonymous"],["DataEmployee"]]},{"operationId":"xP4bN1K6P0CfFAcXUtuamw","operationType":"callMicroflow","parameters":{"AccountPasswordData":["Administration.AccountPasswordData"]},"constants":{"MicroflowName":"Administration.ChangeMyPassword"},"allowedUserRoleSets":[["Administrator"],["User"],["DataEmployee"]]},{"operationId":"A00b89PoLkuR2Gxkv1K3Dg","operationType":"callMicroflow","parameters":{"TestHelper":["Builder.TestHelper"]},"constants":{"MicroflowName":"Solver.ACT_FinishTest"},"allowedUserRoleSets":[["Administrator"],["User"]]},{"operationId":"nxtZMAG+OE+j4Mve29EySg","operationType":"rollback","parameters":{"Objects":["AnyObjectList"]},"constants":{},"allowedUserRoleSets":[["Administrator"],["User"],["Anonymous"],["DataEmployee"]]},{"operationId":"rEIh8UNS9EW5EQDTiQ7wKQ","operationType":"callMicroflow","parameters":{},"constants":{"MicroflowName":"Builder.ACT_GenerateBuilderTests"},"allowedUserRoleSets":[["DataEmployee"]]},{"operationId":"HjB2+x70zE+9H+ryJTEMdw","operationType":"commit","parameters":{"Objects":["AnyObjectList"]},"constants":{},"allowedUserRoleSets":[["Administrator"],["User"],["Anonymous"],["DataEmployee"]]},{"operationId":"+b0ICL3hlEG/JYt2almvVw","operationType":"rollback","parameters":{"Objects":["AnyObjectList"]},"constants":{},"allowedUserRoleSets":[["Administrator"],["User"],["Anonymous"],["DataEmployee"]]},{"operationId":"u5xr+SNzKEChiz52u55pGg","operationType":"rollback","parameters":{"Objects":["AnyObjectList"]},"constants":{},"allowedUserRoleSets":[["Administrator"],["User"],["Anonymous"],["DataEmployee"]]},{"operationId":"70R8GBdz0kOnj+EJupLwGg","operationType":"rollback","parameters":{"Objects":["AnyObjectList"]},"constants":{},"allowedUserRoleSets":[["Administrator"],["User"],["Anonymous"],["DataEmployee"]]},{"operationId":"h1bnstkVu0G5JkP/Pz7YlA","operationType":"rollback","parameters":{"Objects":["AnyObjectList"]},"constants":{},"allowedUserRoleSets":[["Administrator"],["User"],["Anonymous"],["DataEmployee"]]}]