[{"queryId":"Y5Fk2P1oy0KFi4Bvn2vHpw","xPath":null,"microflow":null,"entityPath":"Solver.SolverQuestion","pageName":"Solver.SolvedTests_Web","widgetName":"Solver.SolvedTests_Web.templateGrid1","usedAssociations":["Solver.SolverQuestion/Solver.SolverQuestion_Question/Builder.Question"],"usedAttributes":[],"parameters":{},"allowedUserRoleSets":[["Administrator"],["User"],["Anonymous"],["DataEmployee"]]},{"queryId":"X5pIHW18U0+Gbdf55y7mUw","xPath":null,"microflow":"OQL.DS_ExampleOQL_DataSet","entityPath":null,"pageName":"OQL.ExampleOQL_Result","widgetName":"OQL.ExampleOQL_Result.grid2","usedAssociations":[],"usedAttributes":[],"parameters":{},"allowedUserRoleSets":[["Administrator"],["User"],["Anonymous"],["DataEmployee"]]},{"queryId":"aBPDR3ZoUkm6tAg3tFZ+XA","xPath":null,"microflow":null,"entityPath":"OQL.ExamplePersonResult","pageName":"OQL.ExampleOQL_Result","widgetName":"OQL.ExampleOQL_Result.dataView1","usedAssociations":["OQL.ExamplePersonResult/OQL.ExamplePersonResult_ExamplePerson/OQL.ExamplePerson","OQL.ExamplePersonResult/OQL.Result_MarriedTo/OQL.ExamplePerson"],"usedAttributes":[],"parameters":{"CurrentObject":["OQL.ExamplePersonResult"]},"allowedUserRoleSets":[["Administrator"],["User"],["Anonymous"],["DataEmployee"]]},{"queryId":"GV1Roy+ZXkqtmr6NaJQtqg","xPath":null,"microflow":null,"entityPath":"Builder.Question","pageName":"Builder.MyTests_Web","widgetName":"Builder.MyTests_Web.templateGrid1","usedAssociations":[],"usedAttributes":[],"parameters":{},"allowedUserRoleSets":[["Administrator"],["User"],["Anonymous"],["DataEmployee"]]},{"queryId":"zlY7ofWzo0qyNWhbMX3f6A","xPath":null,"microflow":null,"entityPath":"Solver.SolverQuestion_Question/Builder.Question","pageName":"Solver.TestSolver_Web","widgetName":"Solver.TestSolver_Web.dataView4","usedAssociations":[],"usedAttributes":[],"parameters":{"CurrentObject":["Solver.SolverQuestion"]},"allowedUserRoleSets":[["Administrator"],["User"],["Anonymous"],["DataEmployee"]]},{"queryId":"+vLf8I7GmUG0JwNsJ7p27w","xPath":"//Administration.Account","microflow":null,"entityPath":null,"pageName":"Builder.School_NewEdit","widgetName":"Builder.School_NewEdit.referenceSelector1","usedAssociations":[],"usedAttributes":["Administration.Account/System.User.Name"],"parameters":{},"allowedUserRoleSets":[["Administrator"],["User"],["Anonymous"],["DataEmployee"]]},{"queryId":"fw5WX235f0uqgizXuz6SGw","xPath":"//Builder.School","microflow":null,"entityPath":null,"pageName":"Builder.Course_NewEdit","widgetName":"Builder.Course_NewEdit.referenceSelector1","usedAssociations":[],"usedAttributes":["Builder.School/Builder.School.SchoolType"],"parameters":{},"allowedUserRoleSets":[["Administrator"],["User"],["Anonymous"],["DataEmployee"]]},{"queryId":"XAQEEX0ie0CY+oBfuWkulg","xPath":null,"microflow":"Solver.DS_ActiveSolverQuestion","entityPath":null,"pageName":"Solver.TestSolver_Web","widgetName":"Solver.TestSolver_Web.dataView3","usedAssociations":["Solver.SolverQuestion/Solver.SolverQuestion_Question/Builder.Question"],"usedAttributes":[],"parameters":{"TestHelper":["Builder.TestHelper"]},"allowedUserRoleSets":[["Administrator"],["User"],["Anonymous"],["DataEmployee"]]},{"queryId":"kgPcHtqP/Uub5ovOg886Lw","xPath":null,"microflow":null,"entityPath":"Builder.Test","pageName":"Builder.MyTests_Web","widgetName":"Builder.MyTests_Web.dataView1","usedAssociations":[],"usedAttributes":[],"parameters":{"CurrentObject":["Builder.Test"]},"allowedUserRoleSets":[["Administrator"],["User"],["Anonymous"],["DataEmployee"]]},{"queryId":"1AFTuJAMxkiOtH2hsbI51Q","xPath":"//System.Language","microflow":null,"entityPath":null,"pageName":"Administration.Account_New","widgetName":"Administration.Account_New.referenceSelector1","usedAssociations":[],"usedAttributes":["System.Language/System.Language.Description"],"parameters":{},"allowedUserRoleSets":[["Administrator"],["User"],["Anonymous"],["DataEmployee"]]},{"queryId":"dxeXKVJi30KpJIOJwynQRQ","xPath":null,"microflow":"Administration.RetrieveTimeZones","entityPath":null,"pageName":"Administration.Account_Edit","widgetName":"Administration.Account_Edit.referenceSelector2","usedAssociations":[],"usedAttributes":["System.TimeZone/System.TimeZone.Description"],"parameters":{},"allowedUserRoleSets":[["Administrator"],["User"],["Anonymous"],["DataEmployee"]]},{"queryId":"xd2D1OjhcUiowIHiJkrGSg","xPath":null,"microflow":"Builder.DS_ActiveQuestion","entityPath":null,"pageName":"Builder.TestBuilder_Web","widgetName":"Builder.TestBuilder_Web.dataView3","usedAssociations":[],"usedAttributes":[],"parameters":{"TestHelper":["Builder.TestHelper"]},"allowedUserRoleSets":[["Administrator"],["User"],["Anonymous"],["DataEmployee"]]},{"queryId":"7sZ6zxtGzU6eW68kTN1RJQ","xPath":null,"microflow":null,"entityPath":"Builder.Question_Test/Builder.Question","pageName":"Builder.MyTests_Web","widgetName":"Builder.MyTests_Web.templateGrid1","usedAssociations":[],"usedAttributes":[],"parameters":{"CurrentObject":["Builder.Test"]},"allowedUserRoleSets":[["Administrator"],["User"],["Anonymous"],["DataEmployee"]]},{"queryId":"W3hpzS+nk0iJ0VDLn3xUgQ","xPath":null,"microflow":null,"entityPath":"DataStore.QueryHelper","pageName":"DataStore.Result_Popup","widgetName":"DataStore.Result_Popup.dataView1","usedAssociations":[],"usedAttributes":[],"parameters":{},"allowedUserRoleSets":[["Administrator"],["User"],["Anonymous"],["DataEmployee"]]},{"queryId":"5yTVTomfb0iVoVoTVWrZcw","xPath":"//System.Language","microflow":null,"entityPath":null,"pageName":"Administration.Account_Edit","widgetName":"Administration.Account_Edit.referenceSelector1","usedAssociations":[],"usedAttributes":["System.Language/System.Language.Description"],"parameters":{},"allowedUserRoleSets":[["Administrator"],["User"],["Anonymous"],["DataEmployee"]]},{"queryId":"6CxOJcZKTkyn4Ahxu+4z7A","xPath":null,"microflow":null,"entityPath":"Builder.School","pageName":"Builder.Config_Web","widgetName":"Builder.Config_Web.dataView1","usedAssociations":[],"usedAttributes":[],"parameters":{"CurrentObject":["Builder.School"]},"allowedUserRoleSets":[["Administrator"],["User"],["Anonymous"],["DataEmployee"]]},{"queryId":"rQy9zartJ0Civ3butZgd8g","xPath":null,"microflow":"Administration.RetrieveTimeZones","entityPath":null,"pageName":"Administration.Account_New","widgetName":"Administration.Account_New.referenceSelector2","usedAssociations":[],"usedAttributes":["System.TimeZone/System.TimeZone.Description"],"parameters":{},"allowedUserRoleSets":[["Administrator"],["User"],["Anonymous"],["DataEmployee"]]},{"queryId":"ozzCtNA2bkWjcZmGsF8Aqg","xPath":"//Administration.Account","microflow":null,"entityPath":null,"pageName":"Builder.Course_NewEdit","widgetName":"Builder.Course_NewEdit.referenceSelector2","usedAssociations":[],"usedAttributes":["Administration.Account/System.User.Name"],"parameters":{},"allowedUserRoleSets":[["Administrator"],["User"],["Anonymous"],["DataEmployee"]]},{"queryId":"8zjqv58QEEmEubdfD1gYSw","xPath":"//OQL.ExamplePerson","microflow":null,"entityPath":null,"pageName":"OQL.ExampleOQL_Result","widgetName":"OQL.ExampleOQL_Result.referenceSelector2","usedAssociations":[],"usedAttributes":["OQL.ExamplePerson/OQL.ExamplePerson.Name"],"parameters":{},"allowedUserRoleSets":[["Administrator"],["User"],["Anonymous"],["DataEmployee"]]},{"queryId":"ddZQ98fYlkS7ghkivyFs7A","xPath":null,"microflow":null,"entityPath":"Builder.Lecture_Course/Builder.Lecture","pageName":"Builder.Config_Web","widgetName":"Builder.Config_Web.grid3","usedAssociations":[],"usedAttributes":[],"parameters":{"CurrentObject":["Builder.Course"]},"allowedUserRoleSets":[["Administrator"],["User"],["Anonymous"],["DataEmployee"]]},{"queryId":"eTgICgq/RUe9O5Z33BXxVQ","xPath":null,"microflow":"Builder.DS_SelectableLectures","entityPath":null,"pageName":"Builder.TestBuilder_Web","widgetName":"Builder.TestBuilder_Web.referenceSelector3","usedAssociations":[],"usedAttributes":["Builder.Lecture/Builder.Lecture.LectureName"],"parameters":{"ConnectedSelector":["Builder.ConnectedSelector"]},"allowedUserRoleSets":[["Administrator"],["User"],["Anonymous"],["DataEmployee"]]},{"queryId":"7Co98i15LE+hYRD6yuV0Fg","xPath":null,"microflow":null,"entityPath":"Administration.AccountPasswordData_Account/Administration.Account","pageName":"Administration.Account_New","widgetName":"Administration.Account_New.dataView1","usedAssociations":["Administration.Account/System.UserRoles/System.UserRole","Administration.Account/System.User_Language/System.Language","Administration.Account/System.User_TimeZone/System.TimeZone"],"usedAttributes":[],"parameters":{"CurrentObject":["Administration.AccountPasswordData"]},"allowedUserRoleSets":[["Administrator"],["User"],["Anonymous"],["DataEmployee"]]},{"queryId":"nQaNh/4H90aGqOEIYSAGyg","xPath":null,"microflow":"Builder.DS_SelectableCourses","entityPath":null,"pageName":"Builder.TestBuilder_Web","widgetName":"Builder.TestBuilder_Web.referenceSelector2","usedAssociations":[],"usedAttributes":["Builder.Course/Builder.Course.CourseName"],"parameters":{"ConnectedSelector":["Builder.ConnectedSelector"]},"allowedUserRoleSets":[["Administrator"],["User"],["Anonymous"],["DataEmployee"]]},{"queryId":"SUw2T9jy+UWEciYjgs8sqA","xPath":null,"microflow":null,"entityPath":"Solver.SolverQuestion_SolverTest/Solver.SolverQuestion","pageName":"Solver.SolvedTests_Web","widgetName":"Solver.SolvedTests_Web.templateGrid1","usedAssociations":["Solver.SolverQuestion/Solver.SolverQuestion_Question/Builder.Question"],"usedAttributes":[],"parameters":{"CurrentObject":["Solver.SolverTest"]},"allowedUserRoleSets":[["Administrator"],["User"],["Anonymous"],["DataEmployee"]]},{"queryId":"Y66jFGOvhk+P2q7E6cglvA","xPath":null,"microflow":"OQL.DS_ExampleOQL_Statement","entityPath":null,"pageName":"OQL.ExampleOQL_Result","widgetName":"OQL.ExampleOQL_Result.grid1","usedAssociations":[],"usedAttributes":[],"parameters":{},"allowedUserRoleSets":[["Administrator"],["User"],["Anonymous"],["DataEmployee"]]},{"queryId":"uM1AbeG+9E2DoShsKASetQ","xPath":"//Administration.Account[Name = $Anonymous/Name]","microflow":null,"entityPath":null,"pageName":"Anonymous.ACT_Signup","widgetName":"Retrieve Account from database","usedAssociations":[],"usedAttributes":[],"parameters":{"Anonymous$Name":["String"]},"allowedUserRoleSets":[["Administrator"],["User"],["Anonymous"],["DataEmployee"]]},{"queryId":"oF4u8ZRy6UCFPucxctwFEQ","xPath":null,"microflow":null,"entityPath":"Builder.Question_Test/Builder.Question","pageName":"Builder.SUB_GetCurrentQuestion_BySort","widgetName":"Retrieve list of Question by $Test/Question_Test","usedAssociations":[],"usedAttributes":[],"parameters":{"CurrentObject":["Builder.Test"]},"allowedUserRoleSets":[["Administrator"],["User"],["Anonymous"],["DataEmployee"]]},{"queryId":"iKXOgfX/10SShqFpcthfKg","xPath":"//System.Language","microflow":null,"entityPath":null,"pageName":"Atlas_Core.Atlas_Default","widgetName":"Atlas_Core.LanguageSelectorWidget.languageSelector1","usedAssociations":[],"usedAttributes":["System.Language/System.Language.Description"],"parameters":{},"allowedUserRoleSets":[["Administrator"],["User"],["Anonymous"],["DataEmployee"]]},{"queryId":"8FyS1w1PkEG3oydyCIgH1g","xPath":null,"microflow":null,"entityPath":"System.UserRoles/System.UserRole","pageName":"Administration.Account_New","widgetName":"Administration.Account_New.referenceSetSelector2","usedAssociations":[],"usedAttributes":["System.UserRole/System.UserRole.Name"],"parameters":{"CurrentObject":["Administration.Account"]},"allowedUserRoleSets":[["Administrator"],["User"],["Anonymous"],["DataEmployee"]]},{"queryId":"DZFLTbiPJ0ipRqH7XqDZuw","xPath":"//Builder.School","microflow":null,"entityPath":null,"pageName":"Builder.TestBuilder_Web","widgetName":"Builder.TestBuilder_Web.referenceSelector1","usedAssociations":[],"usedAttributes":["Builder.School/Builder.School.SchoolType"],"parameters":{},"allowedUserRoleSets":[["Administrator"],["User"],["Anonymous"],["DataEmployee"]]},{"queryId":"fsy+pFa9FE+mPA5vxvTshA","xPath":"//System.Language","microflow":null,"entityPath":null,"pageName":"Administration.MyAccount","widgetName":"Administration.MyAccount.referenceSelector1","usedAssociations":[],"usedAttributes":["System.Language/System.Language.Description"],"parameters":{},"allowedUserRoleSets":[["Administrator"],["User"],["Anonymous"],["DataEmployee"]]},{"queryId":"IlU8d9Tv70Gpyaq/Nqr/sg","xPath":null,"microflow":"Builder.DS_SelectableLectures","entityPath":null,"pageName":"Solver.TestSolver_Web","widgetName":"Solver.TestSolver_Web.referenceSelector3","usedAssociations":[],"usedAttributes":["Builder.Lecture/Builder.Lecture.LectureName"],"parameters":{"ConnectedSelector":["Builder.ConnectedSelector"]},"allowedUserRoleSets":[["Administrator"],["User"],["Anonymous"],["DataEmployee"]]},{"queryId":"rKmzqf1kRk+30ks5JtsWkQ","xPath":"//Administration.Account","microflow":null,"entityPath":null,"pageName":"Builder.School_NewEdit","widgetName":"Builder.School_NewEdit.referenceSelector2","usedAssociations":[],"usedAttributes":["Administration.Account/System.User.Name"],"parameters":{},"allowedUserRoleSets":[["Administrator"],["User"],["Anonymous"],["DataEmployee"]]},{"queryId":"Zc+wsEWI3UyU9yO3g+yKVw","xPath":null,"microflow":null,"entityPath":"System.UserRoles/System.UserRole","pageName":"Administration.Account_Edit","widgetName":"Administration.Account_Edit.referenceSetSelector2","usedAssociations":[],"usedAttributes":["System.UserRole/System.UserRole.Name"],"parameters":{"CurrentObject":["Administration.Account"]},"allowedUserRoleSets":[["Administrator"],["User"],["Anonymous"],["DataEmployee"]]},{"queryId":"yn2BX9dIQUKTLaa5Z9U07w","xPath":null,"microflow":null,"entityPath":"Solver.SolverQuestion_SolverTest/Solver.SolverQuestion","pageName":"Solver.TestSolver_Web","widgetName":"Solver.TestSolver_Web.listView1","usedAssociations":[],"usedAttributes":[],"parameters":{"CurrentObject":["Solver.SolverTest"]},"allowedUserRoleSets":[["Administrator"],["User"],["Anonymous"],["DataEmployee"]]},{"queryId":"H1QchaukZEWWXx3xTuTC5w","xPath":"//OQL.ExamplePerson","microflow":null,"entityPath":null,"pageName":"OQL.ExampleOQL_Result","widgetName":"OQL.ExampleOQL_Result.referenceSelector1","usedAssociations":[],"usedAttributes":["OQL.ExamplePerson/OQL.ExamplePerson.Name"],"parameters":{},"allowedUserRoleSets":[["Administrator"],["User"],["Anonymous"],["DataEmployee"]]},{"queryId":"N8AqEiKkuUScSFKpGgANIA","xPath":null,"microflow":null,"entityPath":"Solver.SolverQuestion_Question/Builder.Question","pageName":"Solver.SolvedTests_Web","widgetName":"Solver.SolvedTests_Web.dataView2","usedAssociations":[],"usedAttributes":[],"parameters":{"CurrentObject":["Solver.SolverQuestion"]},"allowedUserRoleSets":[["Administrator"],["User"],["Anonymous"],["DataEmployee"]]},{"queryId":"EI18t7bOhE6PeQL1xPZCaw","xPath":null,"microflow":"OQL.DS_GetQuery","entityPath":null,"pageName":"OQL.Example_Overview","widgetName":"OQL.OQL.dataView1","usedAssociations":[],"usedAttributes":[],"parameters":{},"allowedUserRoleSets":[["Administrator"],["User"],["Anonymous"],["DataEmployee"]]},{"queryId":"vWeQOcMH3km/pvp4ax9yhg","xPath":null,"microflow":null,"entityPath":"Builder.Course","pageName":"Builder.Config_Web","widgetName":"Builder.Config_Web.dataView2","usedAssociations":[],"usedAttributes":[],"parameters":{"CurrentObject":["Builder.Course"]},"allowedUserRoleSets":[["Administrator"],["User"],["Anonymous"],["DataEmployee"]]},{"queryId":"IXRroId5o0ucTm34P+gJSA","xPath":null,"microflow":null,"entityPath":"Builder.Course_School/Builder.Course","pageName":"Builder.Config_Web","widgetName":"Builder.Config_Web.grid2","usedAssociations":[],"usedAttributes":[],"parameters":{"CurrentObject":["Builder.School"]},"allowedUserRoleSets":[["Administrator"],["User"],["Anonymous"],["DataEmployee"]]},{"queryId":"UErIi4cGR0uXbFtvri+Rtg","xPath":null,"microflow":null,"entityPath":"Builder.TestHelper_SolverTest/Solver.SolverTest","pageName":"Solver.TestSolver_Web","widgetName":"Solver.TestSolver_Web.dataView6","usedAssociations":[],"usedAttributes":[],"parameters":{"CurrentObject":["Builder.TestHelper"]},"allowedUserRoleSets":[["Administrator"],["User"],["Anonymous"],["DataEmployee"]]},{"queryId":"wttIImF08EurkskqOTgI0A","xPath":null,"microflow":"Builder.DS_ConnectedSelector","entityPath":null,"pageName":"Solver.TestSolver_Web","widgetName":"Solver.TestSolver_Web.dataView2","usedAssociations":["Builder.ConnectedSelector/Builder.Selected_School/Builder.School","Builder.ConnectedSelector/Builder.Selected_Course/Builder.Course","Builder.ConnectedSelector/Builder.Selected_Lecture/Builder.Lecture"],"usedAttributes":[],"parameters":{},"allowedUserRoleSets":[["Administrator"],["User"],["Anonymous"],["DataEmployee"]]},{"queryId":"bOuFmWeVlkmrC02G0tQ+Zw","xPath":"//Administration.Account","microflow":null,"entityPath":null,"pageName":"Builder.Lecture_NewEdit","widgetName":"Builder.Lecture_NewEdit.referenceSelector2","usedAssociations":[],"usedAttributes":["Administration.Account/System.User.Name"],"parameters":{},"allowedUserRoleSets":[["Administrator"],["User"],["Anonymous"],["DataEmployee"]]},{"queryId":"Hy/2t3zf2kyxjns7y2dkZA","xPath":null,"microflow":null,"entityPath":"Builder.TestHelper_SolverTest/Solver.SolverTest","pageName":"Solver.TestSolver_Web","widgetName":"Solver.TestSolver_Web.dataView5","usedAssociations":[],"usedAttributes":[],"parameters":{"CurrentObject":["Builder.TestHelper"]},"allowedUserRoleSets":[["Administrator"],["User"],["Anonymous"],["DataEmployee"]]},{"queryId":"FJ52tC4X5U+F+c3R1PP8oA","xPath":null,"microflow":"Builder.DS_ConnectedSelector","entityPath":null,"pageName":"Builder.TestBuilder_Web","widgetName":"Builder.TestBuilder_Web.dataView2","usedAssociations":["Builder.ConnectedSelector/Builder.Selected_School/Builder.School","Builder.ConnectedSelector/Builder.Selected_Course/Builder.Course","Builder.ConnectedSelector/Builder.Selected_Lecture/Builder.Lecture"],"usedAttributes":[],"parameters":{},"allowedUserRoleSets":[["Administrator"],["User"],["Anonymous"],["DataEmployee"]]},{"queryId":"2/LeWgwvDEGsDtk2eihiOQ","xPath":"//Administration.Account","microflow":null,"entityPath":null,"pageName":"Builder.Lecture_NewEdit","widgetName":"Builder.Lecture_NewEdit.referenceSelector3","usedAssociations":[],"usedAttributes":["Administration.Account/System.User.Name"],"parameters":{},"allowedUserRoleSets":[["Administrator"],["User"],["Anonymous"],["DataEmployee"]]},{"queryId":"a6pu7dTB/kaMcj6g218VAg","xPath":null,"microflow":null,"entityPath":"Solver.SolverTest","pageName":"Solver.SolvedTests_Web","widgetName":"Solver.SolvedTests_Web.dataView1","usedAssociations":[],"usedAttributes":[],"parameters":{"CurrentObject":["Solver.SolverTest"]},"allowedUserRoleSets":[["Administrator"],["User"],["Anonymous"],["DataEmployee"]]},{"queryId":"b1nu+H2Jm0acXRimw2vjAQ","xPath":null,"microflow":"Extensions.SUB_Account_ByCurrentUser","entityPath":null,"pageName":"QuizApp.Home_Web","widgetName":"QuizApp.Home_Web.dataView1","usedAssociations":["Administration.Account/Administration.Account_City/Extensions.City/Extensions.City_Country/Extensions.Country","Administration.Account/Administration.Account_City/Extensions.City"],"usedAttributes":[],"parameters":{},"allowedUserRoleSets":[["Administrator"],["User"],["Anonymous"],["DataEmployee"]]},{"queryId":"LHgso0euoU2iFCjNBXgzKA","xPath":"//Administration.Account","microflow":null,"entityPath":null,"pageName":"Builder.Course_NewEdit","widgetName":"Builder.Course_NewEdit.referenceSelector3","usedAssociations":[],"usedAttributes":["Administration.Account/System.User.Name"],"parameters":{},"allowedUserRoleSets":[["Administrator"],["User"],["Anonymous"],["DataEmployee"]]},{"queryId":"M6fkYj/+KUOGVv5TTyqt+A","xPath":null,"microflow":null,"entityPath":"Builder.TestHelper_Test/Builder.Test","pageName":"Builder.SUB_GetCurrentQuestion_BySort","widgetName":"Retrieve Test by $TestBuilderHelper/TestHelper_Test","usedAssociations":[],"usedAttributes":[],"parameters":{"CurrentObject":["Builder.TestHelper"]},"allowedUserRoleSets":[["Administrator"],["User"],["Anonymous"],["DataEmployee"]]},{"queryId":"H1RU6LImFU2Nji5poSYYyQ","xPath":"//System.Language","microflow":null,"entityPath":null,"pageName":"Atlas_Core.Atlas_TopBar","widgetName":"Atlas_Core.LanguageSelectorWidget.languageSelector1","usedAssociations":[],"usedAttributes":["System.Language/System.Language.Description"],"parameters":{},"allowedUserRoleSets":[["Administrator"],["User"],["Anonymous"],["DataEmployee"]]},{"queryId":"pJRJo8TIpUOfORQNW3OGjg","xPath":"//Builder.School","microflow":null,"entityPath":null,"pageName":"Solver.TestSolver_Web","widgetName":"Solver.TestSolver_Web.referenceSelector1","usedAssociations":[],"usedAttributes":["Builder.School/Builder.School.SchoolType"],"parameters":{},"allowedUserRoleSets":[["Administrator"],["User"],["Anonymous"],["DataEmployee"]]},{"queryId":"U/Pgr79ZsUqM33AatZI3Aw","xPath":null,"microflow":"Builder.DS_SelectableCourses","entityPath":null,"pageName":"Solver.TestSolver_Web","widgetName":"Solver.TestSolver_Web.referenceSelector2","usedAssociations":[],"usedAttributes":["Builder.Course/Builder.Course.CourseName"],"parameters":{"ConnectedSelector":["Builder.ConnectedSelector"]},"allowedUserRoleSets":[["Administrator"],["User"],["Anonymous"],["DataEmployee"]]}]